aiogzip.py
aiogzip-0.4.dist-info/licenses/LICENSE
aiogzip-0.4.dist-info/METADATA
aiogzip-0.4.dist-info/WHEEL
aiogzip-0.4.dist-info/top_level.txt
aiogzip-0.4.dist-info/RECORD
