Metadata-Version: 2.4
Name: aiogzip
Version: 0.4
Summary: Asynchronous gzip file reader/writer with aiocsv support.
Author-email: Geoff Davis <geoff@keksi.ai>
License: MIT License
Project-URL: Homepage, https://github.com/geoff-davis/aiogzip
Project-URL: Source Code, https://github.com/geoff-davis/aiogzip
Project-URL: Bug Tracker, https://github.com/geoff-davis/aiogzip/issues
Classifier: Programming Language :: Python :: 3
Classifier: License :: OSI Approved :: MIT License
Classifier: Operating System :: OS Independent
Classifier: Framework :: AsyncIO
Classifier: Topic :: System :: Archiving :: Compression
Requires-Python: >=3.8
License-File: LICENSE
Requires-Dist: aiofiles>=23.0.0
Provides-Extra: csv
Requires-Dist: aiocsv>=1.2.0; extra == "csv"
Provides-Extra: dev
Requires-Dist: pytest>=8.0.0; extra == "dev"
Requires-Dist: pytest-asyncio; extra == "dev"
Requires-Dist: pytest-cov>=4.0.0; extra == "dev"
Requires-Dist: psutil; extra == "dev"
Requires-Dist: tomli; python_version < "3.11" and extra == "dev"
Dynamic: license-file
